wasabi2d/__init__.py
wasabi2d/actor.py
wasabi2d/animation.py
wasabi2d/atlas.py
wasabi2d/chain.py
wasabi2d/clock.py
wasabi2d/color.py
wasabi2d/constants.py
wasabi2d/descriptors.py
wasabi2d/game.py
wasabi2d/keyboard.py
wasabi2d/layers.py
wasabi2d/loaders.py
wasabi2d/music.py
wasabi2d/rect.py
wasabi2d/scene.py
wasabi2d/shaders.py
wasabi2d/storage.py
wasabi2d/tone.py
wasabi2d/allocators/__init__.py
wasabi2d/allocators/abstract.py
wasabi2d/allocators/index.py
wasabi2d/allocators/packed.py
wasabi2d/allocators/textures.py
wasabi2d/allocators/vertlists.py
wasabi2d/data/icon.png
wasabi2d/data/roboto_regular.ttf
wasabi2d/effects/__init__.py
wasabi2d/effects/base.py
wasabi2d/effects/base_matrix.py
wasabi2d/effects/bloom.py
wasabi2d/effects/blur.py
wasabi2d/effects/dropshadow.py
wasabi2d/effects/greyscale.py
wasabi2d/effects/pixellate.py
wasabi2d/effects/posterize.py
wasabi2d/effects/punch.py
wasabi2d/effects/sepia.py
wasabi2d/effects/trails.py
wasabi2d/glsl/texquads.frag
wasabi2d/glsl/texquads.vert
wasabi2d/glsl/text.frag
wasabi2d/glsl/postprocess/bloom_blur.frag
wasabi2d/glsl/postprocess/blur.frag
wasabi2d/glsl/postprocess/color_matrix.frag
wasabi2d/glsl/postprocess/copy.frag
wasabi2d/glsl/postprocess/dropshadow_composite.frag
wasabi2d/glsl/postprocess/multisample_blend.frag
wasabi2d/glsl/postprocess/pixellate_average.frag
wasabi2d/glsl/postprocess/pixellate_copy.frag
wasabi2d/glsl/postprocess/posterize.frag
wasabi2d/glsl/postprocess/postprocess.vert
wasabi2d/glsl/postprocess/punch.frag
wasabi2d/glsl/postprocess/trails_composite.frag
wasabi2d/glsl/postprocess/trails_fade.frag
wasabi2d/glsl/primitives/flat_color.frag
wasabi2d/glsl/primitives/flat_color.vert
wasabi2d/glsl/primitives/particle.frag
wasabi2d/glsl/primitives/particle.geom
wasabi2d/glsl/primitives/particle.vert
wasabi2d/glsl/primitives/tile_map.frag
wasabi2d/glsl/primitives/tile_map.geom
wasabi2d/glsl/primitives/tile_map.vert
wasabi2d/glsl/primitives/wide_line.geom
wasabi2d/glsl/primitives/wide_line.vert
wasabi2d-1.4.1.dist-info/licenses/LICENSE
wasabi2d-1.4.1.dist-info/METADATA
wasabi2d-1.4.1.dist-info/WHEEL
wasabi2d-1.4.1.dist-info/top_level.txt
wasabi2d-1.4.1.dist-info/RECORD
