Metadata-Version: 2.4
Name: wasabi2d
Version: 1.4.1
Summary: A convenient 2D OpenGL games framework
Home-page: https://github.com/lordmauve/wasabi2d
Author: Daniel Pope
Author-email: mauve@mauveweb.co.uk
Classifier: Development Status :: 5 - Production/Stable
Classifier: Intended Audience :: Education
Classifier: License :: OSI Approved :: GNU Lesser General Public License v3 (LGPLv3)
Classifier: Programming Language :: Python :: 3.6
Classifier: Programming Language :: Python :: 3.7
Classifier: Programming Language :: Python :: 3.8
Classifier: Topic :: Education
Classifier: Topic :: Games/Entertainment
Requires-Python: >=3.6
License-File: LICENSE
Requires-Dist: pygame>=2.1
Requires-Dist: moderngl>=5.6
Requires-Dist: numpy
Requires-Dist: pyrr
Requires-Dist: sortedcontainers
Requires-Dist: dataclasses; python_version < "3.7"
Requires-Dist: mapbox-earcut==0.12.*
Requires-Dist: bresenham==0.2.*
Dynamic: author
Dynamic: author-email
Dynamic: classifier
Dynamic: description
Dynamic: description-content-type
Dynamic: home-page
Dynamic: license-file
Dynamic: requires-dist
Dynamic: requires-python
Dynamic: summary
